LICENSE
LICENSE_THIRD_PARTY
MANIFEST.in
README.txt
setup.py
django_selenium_test_runner.egg-info/PKG-INFO
django_selenium_test_runner.egg-info/SOURCES.txt
django_selenium_test_runner.egg-info/dependency_links.txt
django_selenium_test_runner.egg-info/not-zip-safe
django_selenium_test_runner.egg-info/top_level.txt
dstest/__init__.py
dstest/mediahandler.py
dstest/selenium-server.jar
dstest/selenium.py
dstest/test_runner.py
dstest/wsgiserver.py
tests/__init__.py
tests/manage.py
tests/runtests.py
tests/settings.py
tests/urls.py
tests/polls/__init__.py
tests/polls/admin.py
tests/polls/models.py
tests/polls/fixtures/tests/data.json
tests/polls/tests/__init__.py
tests/polls/tests/selenium/__init__.py
tests/polls/tests/selenium/test_complete.html
tests/polls/tests/selenium/test_complete.py
tests/polls/tests/selenium/test_simple_login.html
tests/polls/tests/selenium/test_simple_login.py