Metadata-Version: 1.0
Name: django-selenium-test-runner
Version: 0.1.0
Summary: Django Selenium test runner.
